django_typograf-0.1.2.dist-info/top_level.txt
django_typograf-0.1.2.dist-info/DESCRIPTION.rst
django_typograf-0.1.2.dist-info/WHEEL
django_typograf-0.1.2.dist-info/METADATA
django_typograf-0.1.2.dist-info/RECORD
django_typograf-0.1.2.dist-info/metadata.json
django_typograf/exceptions.py
django_typograf/models.py
django_typograf/__init__.py
django_typograf/admin.py
django_typograf/utils.py
