Metadata-Version: 2.0
Name: django-typograf
Version: 0.1.2
Summary: Django package for use typograf in models. 
Home-page: https://github.com/Samael500/django-typograf
Author: Maksim Skorokhod
Author-email: Samael500@gmail.com
License: MIT
Platform: UNKNOWN
Requires-Dist: typograf (>=0.1)
